{"phases": [{"start": 1581, "end": 28941, "label_name": "out_of_body", "label_id": 12}, {"start": 37422, "end": 64782, "label_name": "out_of_body", "label_id": 12}, {"start": 66542, "end": 411473, "label_name": "preparation", "label_id": 0}, {"start": 311550, "end": 327270, "label_name": "out_of_body", "label_id": 12}, {"start": 411473, "end": 866166, "label_name": "gastric_pouch_creation", "label_id": 1}, {"start": 517876, "end": 542276, "label_name": "severe_index", "label_id": 13}, {"start": 585998, "end": 691561, "label_name": "severe_index", "label_id": 13}, {"start": 731002, "end": 833325, "label_name": "severe_index", "label_id": 13}, {"start": 854326, "end": 1129294, "label_name": "severe_index", "label_id": 13}, {"start": 866166, "end": 1215496, "label_name": "cleaning_coagulation", "label_id": 9}, {"start": 1215496, "end": 3581605, "label_name": "gastric_pouch_creation", "label_id": 1}, {"start": 1247257, "end": 1316459, "label_name": "severe_index", "label_id": 13}, {"start": 1881076, "end": 1957278, "label_name": "severe_index", "label_id": 13}, {"start": 2889945, "end": 2906106, "label_name": "severe_index", "label_id": 13}, {"start": 3581605, "end": 5585664, "label_name": "gastrojejunal_anastomosis", "label_id": 3}, {"start": 3581845, "end": 5300976, "label_name": "severe_index", "label_id": 13}, {"start": 5462140, "end": 5466141, "label_name": "severe_index", "label_id": 13}, {"start": 5585664, "end": 6434649, "label_name": "jejunojejunal_anastomosis", "label_id": 7}, {"start": 6185282, "end": 6187282, "label_name": "severe_index", "label_id": 13}, {"start": 6434649, "end": 6575573, "label_name": "jejunal_separation", "label_id": 5}, {"start": 6575573, "end": 6705337, "label_name": "anastomosis_test", "label_id": 4}, {"start": 6705337, "end": 6857581, "label_name": "closure_mesenteric_defect", "label_id": 8}], "steps": [{"start": 66542, "end": 99303, "label_name": "s1_cavity_exploration", "label_id": 1}, {"start": 99303, "end": 267068, "label_name": "s2_trocar_placement", "label_id": 2}, {"start": 267068, "end": 331750, "label_name": "s2_trocar_placement", "label_id": 2}, {"start": 331750, "end": 411473, "label_name": "s3_retractor_placement", "label_id": 3}, {"start": 411473, "end": 598198, "label_name": "s5_his_angle_dissection", "label_id": 5}, {"start": 598198, "end": 780883, "label_name": "s4_crura_dissection", "label_id": 4}, {"start": 780883, "end": 866166, "label_name": "s40_irrigation_aspiration", "label_id": 40}, {"start": 866166, "end": 895967, "label_name": "s0_null_step", "label_id": 0}, {"start": 895967, "end": 917007, "label_name": "s40_irrigation_aspiration", "label_id": 40}, {"start": 917007, "end": 1140454, "label_name": "s39_coagulation", "label_id": 39}, {"start": 1140454, "end": 1215496, "label_name": "s0_null_step", "label_id": 0}, {"start": 1215496, "end": 1465543, "label_name": "s5_his_angle_dissection", "label_id": 5}, {"start": 1465543, "end": 1501744, "label_name": "s0_null_step", "label_id": 0}, {"start": 1501744, "end": 1670829, "label_name": "s6_horizontal_stapling", "label_id": 6}, {"start": 1670829, "end": 1723191, "label_name": "s7_retrogastric_dissection", "label_id": 7}, {"start": 1723191, "end": 1754512, "label_name": "s4_crura_dissection", "label_id": 4}, {"start": 1754512, "end": 1957198, "label_name": "s7_retrogastric_dissection", "label_id": 7}, {"start": 1957198, "end": 2428932, "label_name": "s8_vertical_stapling", "label_id": 8}, {"start": 2428932, "end": 2496934, "label_name": "s40_irrigation_aspiration", "label_id": 40}, {"start": 2496934, "end": 2672939, "label_name": "s8_vertical_stapling", "label_id": 8}, {"start": 2672939, "end": 2689659, "label_name": "s40_irrigation_aspiration", "label_id": 40}, {"start": 2689659, "end": 2719660, "label_name": "s8_vertical_stapling", "label_id": 8}, {"start": 2719660, "end": 2918946, "label_name": "s7_retrogastric_dissection", "label_id": 7}, {"start": 2918946, "end": 2981588, "label_name": "s40_irrigation_aspiration", "label_id": 40}, {"start": 2981588, "end": 3035189, "label_name": "s11_gastric_opening", "label_id": 11}, {"start": 3035189, "end": 3051430, "label_name": "s22_gastric_tube_placement", "label_id": 22}, {"start": 3051430, "end": 3103911, "label_name": "s40_irrigation_aspiration", "label_id": 40}, {"start": 3103911, "end": 3173633, "label_name": "s8_vertical_stapling", "label_id": 8}, {"start": 3173633, "end": 3279437, "label_name": "s7_retrogastric_dissection", "label_id": 7}, {"start": 3279437, "end": 3315118, "label_name": "s8_vertical_stapling", "label_id": 8}, {"start": 3315118, "end": 3371879, "label_name": "s7_retrogastric_dissection", "label_id": 7}, {"start": 3371879, "end": 3581605, "label_name": "s45_specimen_retrieval", "label_id": 45}, {"start": 3581605, "end": 3742650, "label_name": "s15_treitz_angle_identification", "label_id": 15}, {"start": 3742650, "end": 3845053, "label_name": "s16_biliary_limb_measurement", "label_id": 16}, {"start": 3845053, "end": 3973697, "label_name": "s17_jejunum_opening", "label_id": 17}, {"start": 3973697, "end": 4018578, "label_name": "s22_gastric_tube_placement", "label_id": 22}, {"start": 4018578, "end": 4074980, "label_name": "s40_irrigation_aspiration", "label_id": 40}, {"start": 4074980, "end": 5295296, "label_name": "s19_gastrojejunal_defect_closing", "label_id": 19}, {"start": 5295296, "end": 5331817, "label_name": "s40_irrigation_aspiration", "label_id": 40}, {"start": 5331817, "end": 5585664, "label_name": "s26_gastrojejunal_anastomosis_reinforcement", "label_id": 26}, {"start": 5585664, "end": 5635186, "label_name": "s29_biliary_limb_opening", "label_id": 29}, {"start": 5635186, "end": 5728788, "label_name": "s30_alimentary_limb_measurement", "label_id": 30}, {"start": 5728788, "end": 5771549, "label_name": "s31_alimentary_limb_opening", "label_id": 31}, {"start": 5771549, "end": 5843632, "label_name": "s32_jejunojejunal_stapling", "label_id": 32}, {"start": 5843632, "end": 6434649, "label_name": "s33_jejunojejunal_defect_closing", "label_id": 33}, {"start": 6434649, "end": 6496171, "label_name": "s20_mesenteric_opening", "label_id": 20}, {"start": 6496171, "end": 6575573, "label_name": "s21_jejunal_section", "label_id": 21}, {"start": 6575573, "end": 6589373, "label_name": "s23_jejunal_clamping", "label_id": 23}, {"start": 6589373, "end": 6647335, "label_name": "s24_ink_injection", "label_id": 24}, {"start": 6647335, "end": 6705337, "label_name": "s25_visual_assessment", "label_id": 25}, {"start": 6705337, "end": 6809980, "label_name": "s36_mesenteric_defect_exposure", "label_id": 36}, {"start": 6809980, "end": 6857581, "label_name": "s37_mesenteric_defect_closing", "label_id": 37}]}