{"phases": [{"start": 0, "end": 292860, "label_name": "preparation", "label_id": 0}, {"start": 107300, "end": 124900, "label_name": "out_of_body", "label_id": 12}, {"start": 292860, "end": 1573220, "label_name": "gastric_pouch_creation", "label_id": 1}, {"start": 1573220, "end": 1789220, "label_name": "omentum_division", "label_id": 2}, {"start": 1789220, "end": 3048020, "label_name": "gastrojejunal_anastomosis", "label_id": 3}, {"start": 2280420, "end": 2315660, "label_name": "out_of_body", "label_id": 12}, {"start": 3048020, "end": 3565820, "label_name": "closure_petersen_space", "label_id": 6}, {"start": 3076020, "end": 3089820, "label_name": "out_of_body", "label_id": 12}, {"start": 3565820, "end": 3652140, "label_name": "jejunal_separation", "label_id": 5}, {"start": 3652140, "end": 5604540, "label_name": "jejunojejunal_anastomosis", "label_id": 7}, {"start": 4280500, "end": 4306180, "label_name": "out_of_body", "label_id": 12}, {"start": 5604540, "end": 6085140, "label_name": "closure_mesenteric_defect", "label_id": 8}, {"start": 6085140, "end": 6288580, "label_name": "anastomosis_test", "label_id": 4}, {"start": 6288580, "end": 6653900, "label_name": "gastrojejunal_anastomosis", "label_id": 3}, {"start": 6465220, "end": 6481460, "label_name": "out_of_body", "label_id": 12}, {"start": 6653900, "end": 6973260, "label_name": "cleaning_coagulation", "label_id": 9}, {"start": 6793580, "end": 6811500, "label_name": "out_of_body", "label_id": 12}, {"start": 6814220, "end": 6816820, "label_name": "out_of_body", "label_id": 12}, {"start": 6973260, "end": 7212020, "label_name": "disassembling", "label_id": 10}, {"start": 7075140, "end": 7076300, "label_name": "out_of_body", "label_id": 12}, {"start": 7088300, "end": 7091940, "label_name": "out_of_body", "label_id": 12}, {"start": 7210620, "end": 7212020, "label_name": "out_of_body", "label_id": 12}], "steps": [{"start": 0, "end": 37140, "label_name": "s2_trocar_placement", "label_id": 2}, {"start": 37140, "end": 63900, "label_name": "s3_retractor_placement", "label_id": 3}, {"start": 63900, "end": 95020, "label_name": "s39_coagulation", "label_id": 39}, {"start": 95020, "end": 125380, "label_name": "s3_retractor_placement", "label_id": 3}, {"start": 125380, "end": 292860, "label_name": "s3_retractor_placement", "label_id": 3}, {"start": 292860, "end": 382020, "label_name": "s4_crura_dissection", "label_id": 4}, {"start": 382020, "end": 609260, "label_name": "s5_his_angle_dissection", "label_id": 5}, {"start": 609260, "end": 677220, "label_name": "s6_horizontal_stapling", "label_id": 6}, {"start": 677220, "end": 745900, "label_name": "s7_retrogastric_dissection", "label_id": 7}, {"start": 745900, "end": 981260, "label_name": "s8_vertical_stapling", "label_id": 8}, {"start": 981260, "end": 1042540, "label_name": "s7_retrogastric_dissection", "label_id": 7}, {"start": 1042540, "end": 1246420, "label_name": "s8_vertical_stapling", "label_id": 8}, {"start": 1246420, "end": 1291740, "label_name": "s7_retrogastric_dissection", "label_id": 7}, {"start": 1291740, "end": 1336820, "label_name": "s8_vertical_stapling", "label_id": 8}, {"start": 1336820, "end": 1471060, "label_name": "s7_retrogastric_dissection", "label_id": 7}, {"start": 1471060, "end": 1573220, "label_name": "s11_gastric_opening", "label_id": 11}, {"start": 1573220, "end": 1640180, "label_name": "s12_omental_lifting", "label_id": 12}, {"start": 1640180, "end": 1789220, "label_name": "s13_omental_section", "label_id": 13}, {"start": 1789220, "end": 1818140, "label_name": "s15_treitz_angle_identification", "label_id": 15}, {"start": 1818140, "end": 1887740, "label_name": "s16_biliary_limb_measurement", "label_id": 16}, {"start": 1887740, "end": 1926220, "label_name": "s17_jejunum_opening", "label_id": 17}, {"start": 1926220, "end": 2184700, "label_name": "s43_calibration", "label_id": 43}, {"start": 2184700, "end": 2315900, "label_name": "s18_gastrojejunal_stapling", "label_id": 18}, {"start": 2315900, "end": 2407900, "label_name": "s18_gastrojejunal_stapling", "label_id": 18}, {"start": 2407900, "end": 3048020, "label_name": "s19_gastrojejunal_defect_closing", "label_id": 19}, {"start": 3048020, "end": 3090260, "label_name": "s27_petersen_space_exposure", "label_id": 27}, {"start": 3090260, "end": 3270100, "label_name": "s27_petersen_space_exposure", "label_id": 27}, {"start": 3270100, "end": 3565820, "label_name": "s28_petersen_space_closing", "label_id": 28}, {"start": 3565820, "end": 3621580, "label_name": "s20_mesenteric_opening", "label_id": 20}, {"start": 3621580, "end": 3652140, "label_name": "s21_jejunal_section", "label_id": 21}, {"start": 3652140, "end": 3696300, "label_name": "s29_biliary_limb_opening", "label_id": 29}, {"start": 3696300, "end": 3763820, "label_name": "s30_alimentary_limb_measurement", "label_id": 30}, {"start": 3763820, "end": 3804620, "label_name": "s31_alimentary_limb_opening", "label_id": 31}, {"start": 3804620, "end": 4052220, "label_name": "s32_jejunojejunal_stapling", "label_id": 32}, {"start": 4052220, "end": 4306620, "label_name": "s43_calibration", "label_id": 43}, {"start": 4306620, "end": 5604540, "label_name": "s33_jejunojejunal_defect_closing", "label_id": 33}, {"start": 5604540, "end": 5647180, "label_name": "s36_mesenteric_defect_exposure", "label_id": 36}, {"start": 5647180, "end": 6085140, "label_name": "s37_mesenteric_defect_closing", "label_id": 37}, {"start": 6085140, "end": 6141660, "label_name": "s22_gastric_tube_placement", "label_id": 22}, {"start": 6141660, "end": 6150220, "label_name": "s23_jejunal_clamping", "label_id": 23}, {"start": 6150220, "end": 6179740, "label_name": "s24_ink_injection", "label_id": 24}, {"start": 6179740, "end": 6288580, "label_name": "s25_visual_assessment", "label_id": 25}, {"start": 6288580, "end": 6481580, "label_name": "s26_gastrojejunal_anastomosis_reinforcement", "label_id": 26}, {"start": 6481580, "end": 6653900, "label_name": "s26_gastrojejunal_anastomosis_reinforcement", "label_id": 26}, {"start": 6653900, "end": 6816780, "label_name": "s39_coagulation", "label_id": 39}, {"start": 6816780, "end": 6973260, "label_name": "s39_coagulation", "label_id": 39}, {"start": 6973260, "end": 7092100, "label_name": "s42_trocar_removal", "label_id": 42}, {"start": 7092100, "end": 7212020, "label_name": "s42_trocar_removal", "label_id": 42}]}